{  
    "dataDirectory": "F:/phild",   
    "directoryStructure": [
        "experimentName",
        "animal",
        "date",
        "time"
    ],
    "experimentName": "cv_pilot1",
    "animal": "m15",
    "recordLengthinSeconds": 0,
    "traceDisplay": {
        "enabled": true,
        "type": "scrolling",
        "windowX": 100,
        "windowY": 100,
        "windowWidth": 600,
        "windowHeight": 800
    },
    "COMMENT_devices": "'devices' defines all input and output devices to the software.",
    "COMMENT_devices2": "The currently supported 'deviceType' can be found in the deviceConfigs/videoDevices.json file and also are displayed in the main window of the software when first loaded.",
    "devices": {
        "COMMENT_miniscopes": "This is a JSON object of miniscopes along with their parameters. Generally you will only have 1 entry here.",
        "miniscopes": {
            "miniscope_top": {
                "deviceType": "Miniscope_V4_BNO",
				"headOrientation": {
					"enabled": true,
                    "filterBadData": true,
                    "COMMENT_plotTrace": "Add or remove 'roll' 'pitch' and/or 'yaw' to define which get plotted in the time trace display.",
                    "plotTrace": []
                },
                "deviceID": 1,
                "showSaturation": true,
                "compression": "GREY",
                "framesPerFile": 1000,
                "windowScale": 1,
                "windowX": 800,
                "windowY": 100,
                "gain": "High", "COMMENT_gain": "Low, Medium, High are 1x, 2x, and 3.5x",
                "ewl": 0,
                "led0": 0,
                "frameRate": "30FPS"
            },
            "miniscope_side": {
                "deviceType": "Miniscope_V4_BNO",
				"headOrientation": {
					"enabled": true,
                    "filterBadData": true,
                    "COMMENT_plotTrace": "Add or remove 'roll' 'pitch' and/or 'yaw' to define which get plotted in the time trace display.",
                    "plotTrace": []
                },
                "deviceID": 0,
                "showSaturation": true,
                "compression": "GREY",
                "framesPerFile": 1000,
                "windowScale": 1,
                "windowX": 800,
                "windowY": 100,
                "gain": "High", "COMMENT_gain": "Low, Medium, High are 1x, 2x, and 3.5x",
                "ewl": -32,
                "led0": 28,
                "frameRate": "30FPS"
            }
        },
        "cameras": {}
    }
}
